pyqrcodeng/__init__.py
pyqrcodeng/builder.py
pyqrcodeng/cli.py
pyqrcodeng/qrspecial.py
pyqrcodeng/tables.py
PyQRCodeNG-1.3.6.dist-info/LICENSE
PyQRCodeNG-1.3.6.dist-info/METADATA
PyQRCodeNG-1.3.6.dist-info/WHEEL
PyQRCodeNG-1.3.6.dist-info/entry_points.txt
PyQRCodeNG-1.3.6.dist-info/top_level.txt
PyQRCodeNG-1.3.6.dist-info/RECORD
